README.rst
pymsgq.py
setup.py
pymsgq.egg-info/PKG-INFO
pymsgq.egg-info/SOURCES.txt
pymsgq.egg-info/dependency_links.txt
pymsgq.egg-info/top_level.txt